{"nodes": [{"id": "readme_ai_voice_bot", "label": "ai-voice-bot", "file_type": "document", "source_file": "README.md", "source_location": null, "source_url": null, "captured_at": null, "author": null, "contributor": null}, {"id": "readme_ai_powered_voice_chatbot", "label": "AI-Powered Voice-Enabled Chatbot", "file_type": "concept", "source_file": "README.md", "source_location": "1", "source_url": null, "captured_at": null, "author": null, "contributor": null}, {"id": "readme_authentication", "label": "Authentication", "file_type": "concept", "source_file": "README.md", "source_location": "1", "source_url": null, "captured_at": null, "author": null, "contributor": null}, {"id": "readme_real_time_conversation", "label": "Real-Time Conversation", "file_type": "concept", "source_file": "README.md", "source_location": "1", "source_url": null, "captured_at": null, "author": null, "contributor": null}, {"id": "readme_ai_integration", "label": "AI Integration", "file_type": "concept", "source_file": "README.md", "source_location": "1", "source_url": null, "captured_at": null, "author": null, "contributor": null}, {"id": "readme_grok_api", "label": "Grok API", "file_type": "concept", "source_file": "README.md", "source_location": "1", "source_url": null, "captured_at": null, "author": null, "contributor": null}], "edges": [{"source": "readme_ai_voice_bot", "target": "readme_ai_powered_voice_chatbot", "relation": "references", "confidence": "EXTRACTED", "confidence_score": 1.0, "source_file": "README.md", "source_location": "1", "weight": 1.0}, {"source": "readme_ai_voice_bot", "target": "readme_authentication", "relation": "references", "confidence": "EXTRACTED", "confidence_score": 1.0, "source_file": "README.md", "source_location": "1", "weight": 1.0}, {"source": "readme_ai_voice_bot", "target": "readme_real_time_conversation", "relation": "references", "confidence": "EXTRACTED", "confidence_score": 1.0, "source_file": "README.md", "source_location": "1", "weight": 1.0}, {"source": "readme_ai_voice_bot", "target": "readme_ai_integration", "relation": "references", "confidence": "EXTRACTED", "confidence_score": 1.0, "source_file": "README.md", "source_location": "1", "weight": 1.0}, {"source": "readme_ai_voice_bot", "target": "readme_grok_api", "relation": "references", "confidence": "EXTRACTED", "confidence_score": 1.0, "source_file": "README.md", "source_location": "1", "weight": 1.0}], "hyperedges": [{"id": "project_capabilities", "label": "ai-voice-bot Capabilities", "nodes": ["readme_ai_powered_voice_chatbot", "readme_authentication", "readme_real_time_conversation", "readme_ai_integration", "readme_grok_api"], "relation": "form", "confidence": "EXTRACTED", "confidence_score": 1.0, "source_file": "README.md"}]}